{
"type": "FeatureCollection",
"name": "polling_centers",
"crs": { "type": "name", "properties": { "name": "urn:ogc:def:crs:OGC:1.3:CRS84" } },
"features": [
{ "type": "Feature", "id": 1, "properties": { "Name": "kml_1", "description": "<center><table><tr><th colspan='2' align='center'><em>Attributes</em></th></tr><tr bgcolor=\"#E3E3F3\">\n<th>objectid</th>\n<td>1</td>\n</tr><tr bgcolor=\"\">\n<th>label2</th>\n<td>Weed & Pest 7575 S Hwy 89</td>\n</tr><tr bgcolor=\"#E3E3F3\">\n<th>display</th>\n<td>T</td>\n</tr></table></center>", "tessellate": -1, "extrude": 0, "visibility": -1 }, "geometry": { "type": "Point", "coordinates": [ -110.742932605668997, 43.371901738443398, 0.0 ] } },
{ "type": "Feature", "id": 2, "properties": { "Name": "kml_2", "description": "<center><table><tr><th colspan='2' align='center'><em>Attributes</em></th></tr><tr bgcolor=\"#E3E3F3\">\n<th>objectid</th>\n<td>2</td>\n</tr><tr bgcolor=\"\">\n<th>label2</th>\n<td>Old Wilson School Community Center</td>\n</tr><tr bgcolor=\"#E3E3F3\">\n<th>display</th>\n<td>T</td>\n</tr></table></center>", "tessellate": -1, "extrude": 0, "visibility": -1 }, "geometry": { "type": "Point", "coordinates": [ -110.875183382713004, 43.500932577604601, 0.0 ] } },
{ "type": "Feature", "id": 3, "properties": { "Name": "kml_3", "description": "<center><table><tr><th colspan='2' align='center'><em>Attributes</em></th></tr><tr bgcolor=\"#E3E3F3\">\n<th>objectid</th>\n<td>3</td>\n</tr><tr bgcolor=\"\">\n<th>label2</th>\n<td>Teton County Library</td>\n</tr><tr bgcolor=\"#E3E3F3\">\n<th>display</th>\n<td>T</td>\n</tr></table></center>", "tessellate": -1, "extrude": 0, "visibility": -1 }, "geometry": { "type": "Point", "coordinates": [ -110.779775318009996, 43.471770758477902, 0.0 ] } },
{ "type": "Feature", "id": 4, "properties": { "Name": "kml_4", "description": "<center><table><tr><th colspan='2' align='center'><em>Attributes</em></th></tr><tr bgcolor=\"#E3E3F3\">\n<th>objectid</th>\n<td>4</td>\n</tr><tr bgcolor=\"\">\n<th>label2</th>\n<td>Parks & Recreation Center</td>\n</tr><tr bgcolor=\"#E3E3F3\">\n<th>display</th>\n<td>T</td>\n</tr></table></center>", "tessellate": -1, "extrude": 0, "visibility": -1 }, "geometry": { "type": "Point", "coordinates": [ -110.759399591171999, 43.482527807523702, 0.0 ] } },
{ "type": "Feature", "id": 5, "properties": { "Name": "kml_5", "description": "<center><table><tr><th colspan='2' align='center'><em>Attributes</em></th></tr><tr bgcolor=\"#E3E3F3\">\n<th>objectid</th>\n<td>5</td>\n</tr><tr bgcolor=\"\">\n<th>label2</th>\n<td>Alta Library</td>\n</tr><tr bgcolor=\"#E3E3F3\">\n<th>display</th>\n<td>T</td>\n</tr></table></center>", "tessellate": -1, "extrude": 0, "visibility": -1 }, "geometry": { "type": "Point", "coordinates": [ -111.035980542692997, 43.755155622934801, 0.0 ] } },
{ "type": "Feature", "id": 6, "properties": { "Name": "kml_6", "description": "<center><table><tr><th colspan='2' align='center'><em>Attributes</em></th></tr><tr bgcolor=\"#E3E3F3\">\n<th>objectid</th>\n<td>7</td>\n</tr><tr bgcolor=\"\">\n<th>label2</th>\n<td>Early Voting Center and Secure Drop Box</td>\n</tr><tr bgcolor=\"#E3E3F3\">\n<th>display</th>\n<td>T</td>\n</tr></table></center>", "tessellate": -1, "extrude": 0, "visibility": -1 }, "geometry": { "type": "Point", "coordinates": [ -110.758671802614003, 43.4772784563676, 0.0 ] } }
]
}
